{
	"animations": [
		{
			"loop": false,
			"offsets": [
				3,
				-1
			],
			"anim": "singDOWN",
			"fps": 24,
			"name": "Asriel DOWN NOTE",
			"indices": []
		},
		{
			"loop": false,
			"offsets": [
				9,
				36
			],
			"anim": "singUP",
			"fps": 24,
			"name": "Asriel UP NOTE",
			"indices": []
		},
		{
			"offsets": [
				15,
				-1
			],
			"loop": false,
			"fps": 24,
			"anim": "singRIGHT",
			"indices": [],
			"name": "Asriel LEFT NOTE"
		},
		{
			"offsets": [
				10,
				-1
			],
			"loop": false,
			"fps": 24,
			"anim": "singLEFT",
			"indices": [],
			"name": "Asriel RIGHT NOTE"
		},
		{
			"offsets": [
				-3,
				-1
			],
			"loop": false,
			"fps": 30,
			"anim": "idle",
			"indices": [],
			"name": "Asriel Idle"
		}
	],
	"no_antialiasing": true,
	"image": "characters/asrel-2",
	"position": [
		150,
		360
	],
	"healthicon": "soul-asrel",
	"flip_x": false,
	"healthbar_colors": [
		0,
		0,
		0
	],
	"camera_position": [
		-360,
		-330
	],
	"sing_duration": 4,
	"scale": 6.2
}